pywhatsup/__init__.py
pywhatsup-0.0.1.dist-info/LICENSE
pywhatsup-0.0.1.dist-info/METADATA
pywhatsup-0.0.1.dist-info/WHEEL
pywhatsup-0.0.1.dist-info/top_level.txt
pywhatsup-0.0.1.dist-info/RECORD
