Metadata-Version: 2.1
Name: pywhatsup
Version: 0.0.1
Summary: Python WhatsUp Gold API wrapper
Home-page: https://github.com/peterbaumert/pywhatsup
Author: Peter Baumert
Classifier: Programming Language :: Python :: 3
Classifier: License :: OSI Approved :: MIT License
Classifier: Operating System :: OS Independent
Requires-Python: >=3.6
License-File: LICENSE
